{
	"info": {
		"_postman_id": "2acfe589-c1d3-4b7d-9978-82f13abb2717",
		"name": "coleccion API libros",
		"schema": "https://schema.getpostman.com/json/collection/v2.1.0/collection.json",
		"_exporter_id": "24185643",
		"_collection_link": "https://galactic-meadow-737013.postman.co/workspace/Curso-de-Postman-GeekQA~9cbc6a84-2b3d-4100-a7df-cdd77d51da8a/collection/24185643-2acfe589-c1d3-4b7d-9978-82f13abb2717?action=share&creator=24185643&source=collection_link"
	},
	"item": [
		{
			"name": "consulta libros",
			"item": [
				{
					"name": "Consultar libro x ISBN",
					"request": {
						"method": "GET",
						"header": [],
						"url": {
							"raw": "https://bookstore.demoqa.com/BookStore/v1/Book?ISBN=9781449325862",
							"protocol": "https",
							"host": [
								"bookstore",
								"demoqa",
								"com"
							],
							"path": [
								"BookStore",
								"v1",
								"Book"
							],
							"query": [
								{
									"key": "ISBN",
									"value": "9781449325862"
								}
							]
						}
					},
					"response": []
				}
			]
		},
		{
			"name": "traer libros",
			"request": {
				"method": "GET",
				"header": []
			},
			"response": []
		}
	]
}